<?xml version="1.0" encoding="UTF-8"?>
<GenRun Id="synth_1" LaunchPart="xc7z020clg400-1" LaunchTime="1706375895">
  <File Type="VDS-TIMING-PB" Name="zybo_top_wrapper_timing_summary_synth.pb"/>
  <File Type="VDS-TIMINGSUMMARY" Name="zybo_top_wrapper_timing_summary_synth.rpt"/>
  <File Type="RDS-DCP" Name="zybo_top_wrapper.dcp"/>
  <File Type="RDS-UTIL-PB" Name="zybo_top_wrapper_utilization_synth.pb"/>
  <File Type="RDS-UTIL" Name="zybo_top_wrapper_utilization_synth.rpt"/>
  <File Type="RDS-PROPCONSTRS" Name="zybo_top_wrapper_drc_synth.rpt"/>
  <File Type="RDS-RDS" Name="zybo_top_wrapper.vds"/>
  <File Type="PA-TCL" Name="zybo_top_wrapper.tcl"/>
  <FileSet Name="sources" Type="DesignSrcs" RelSrcDir="$PSRCDIR/sources_1">
    <Filter Type="Srcs"/>
    <File Path="$PPRDIR/../sourcecode/surrounding_modules/rst_gen.sv">
      <FileInfo>
        <Attr Name="UsedIn" Val="synthesis"/>
        <Attr Name="UsedIn" Val="implementation"/>
        <Attr Name="UsedIn" Val="simulation"/>
      </FileInfo>
    </File>
    <File Path="$PPRDIR/../sourcecode/surrounding_modules/rst_gen_wrap.v">
      <FileInfo>
        <Attr Name="UsedIn" Val="synthesis"/>
        <Attr Name="UsedIn" Val="implementation"/>
        <Attr Name="UsedIn" Val="simulation"/>
      </FileInfo>
    </File>
    <File Path="$PPRDIR/../sourcecode/rgb_brightener.sv">
      <FileInfo>
        <Attr Name="UsedIn" Val="synthesis"/>
        <Attr Name="UsedIn" Val="implementation"/>
        <Attr Name="UsedIn" Val="simulation"/>
      </FileInfo>
    </File>
    <File Path="$PPRDIR/../sourcecode/rgb_grayscaler_refined.sv">
      <FileInfo>
        <Attr Name="UsedIn" Val="synthesis"/>
        <Attr Name="UsedIn" Val="implementation"/>
        <Attr Name="UsedIn" Val="simulation"/>
      </FileInfo>
    </File>
    <File Path="$PPRDIR/../sourcecode/surrounding_modules/rgb_mux.sv">
      <FileInfo>
        <Attr Name="UsedIn" Val="synthesis"/>
        <Attr Name="UsedIn" Val="implementation"/>
        <Attr Name="UsedIn" Val="simulation"/>
      </FileInfo>
    </File>
    <File Path="$PPRDIR/../sourcecode/rgb_proc.sv">
      <FileInfo>
        <Attr Name="UsedIn" Val="synthesis"/>
        <Attr Name="UsedIn" Val="implementation"/>
        <Attr Name="UsedIn" Val="simulation"/>
      </FileInfo>
    </File>
    <File Path="$PPRDIR/../sourcecode/surrounding_modules/rgb_reg.sv">
      <FileInfo>
        <Attr Name="UsedIn" Val="synthesis"/>
        <Attr Name="UsedIn" Val="implementation"/>
        <Attr Name="UsedIn" Val="simulation"/>
      </FileInfo>
    </File>
    <File Path="$PPRDIR/../sourcecode/surrounding_modules/rgb_spill_reg.sv">
      <FileInfo>
        <Attr Name="UsedIn" Val="synthesis"/>
        <Attr Name="UsedIn" Val="implementation"/>
        <Attr Name="UsedIn" Val="simulation"/>
      </FileInfo>
    </File>
    <File Path="$PPRDIR/../sourcecode/surrounding_modules/spill_register.sv">
      <FileInfo>
        <Attr Name="UsedIn" Val="synthesis"/>
        <Attr Name="UsedIn" Val="implementation"/>
        <Attr Name="UsedIn" Val="simulation"/>
      </FileInfo>
    </File>
    <File Path="$PPRDIR/../sourcecode/surrounding_modules/stream_demux.sv">
      <FileInfo>
        <Attr Name="UsedIn" Val="synthesis"/>
        <Attr Name="UsedIn" Val="implementation"/>
        <Attr Name="UsedIn" Val="simulation"/>
      </FileInfo>
    </File>
    <File Path="$PPRDIR/../sourcecode/surrounding_modules/stream_mux.sv">
      <FileInfo>
        <Attr Name="UsedIn" Val="synthesis"/>
        <Attr Name="UsedIn" Val="implementation"/>
        <Attr Name="UsedIn" Val="simulation"/>
      </FileInfo>
    </File>
    <File Path="$PPRDIR/../sourcecode/surrounding_modules/rgb_proc_wrap.v">
      <FileInfo>
        <Attr Name="UsedIn" Val="synthesis"/>
        <Attr Name="UsedIn" Val="implementation"/>
        <Attr Name="UsedIn" Val="simulation"/>
      </FileInfo>
    </File>
    <File Path="$PSRCDIR/sources_1/bd/zybo_top/zybo_top.bd">
      <FileInfo>
        <Attr Name="UsedIn" Val="synthesis"/>
        <Attr Name="UsedIn" Val="implementation"/>
        <Attr Name="UsedIn" Val="simulation"/>
      </FileInfo>
    </File>
    <File Path="$PSRCDIR/sources_1/bd/zybo_top/hdl/zybo_top_wrapper.v">
      <FileInfo>
        <Attr Name="UsedIn" Val="synthesis"/>
        <Attr Name="UsedIn" Val="implementation"/>
        <Attr Name="UsedIn" Val="simulation"/>
      </FileInfo>
    </File>
    <Config>
      <Option Name="DesignMode" Val="RTL"/>
      <Option Name="TopModule" Val="zybo_top_wrapper"/>
    </Config>
  </FileSet>
  <FileSet Name="constrs_in" Type="Constrs" RelSrcDir="$PSRCDIR/constrs_1">
    <Filter Type="Constrs"/>
    <File Path="$PPRDIR/constraints/zybo-z7.xdc">
      <FileInfo>
        <Attr Name="UsedIn" Val="synthesis"/>
        <Attr Name="UsedIn" Val="implementation"/>
      </FileInfo>
    </File>
    <Config>
      <Option Name="ConstrsType" Val="XDC"/>
    </Config>
  </FileSet>
  <Strategy Version="1" Minor="2">
    <StratHandle Name="Flow_PerfOptimized_high" Flow="Vivado Synthesis 2017"/>
    <Step Id="synth_design">
      <Option Id="ShregMinSize">5</Option>
      <Option Id="KeepEquivalentRegisters">1</Option>
      <Option Id="FsmExtraction">1</Option>
      <Option Id="ResourceSharing">2</Option>
      <Option Id="NoCombineLuts">1</Option>
      <Option Id="RepFanoutThreshold">400</Option>
      <Option Id="ReTiming">1</Option>
    </Step>
  </Strategy>
</GenRun>
